mcp_server_altibase/__init__.py
mcp_server_altibase/server.py
mcp_server_altibase-0.0.3.dist-info/METADATA
mcp_server_altibase-0.0.3.dist-info/WHEEL
mcp_server_altibase-0.0.3.dist-info/entry_points.txt
mcp_server_altibase-0.0.3.dist-info/licenses/LICENSE
mcp_server_altibase-0.0.3.dist-info/RECORD
