Metadata-Version: 2.4
Name: mcp-server-altibase
Version: 0.0.3
Summary: A simple Altibase MCP server
License-File: LICENSE
Requires-Python: >=3.10
Requires-Dist: mcp>=1.0.0
Requires-Dist: pyodbc>=5.0.1
